{
  "id": "hucaen-module",
  "title": "Hucaen World Setting",
  "version": "#{VERSION}#",
  "library": "false",
  "manifestPlusVersion": "1.2.0",
  "compatibility": {
    "minimum": 11,
    "verified": 12,
    "maximum": 13
  },
  "scripts":[
    "scripts/hucaen.js"
  ],
  "description": "Setting-specific info about Hucaen.",
  "authors": [
    {
      "name": "Cornelius H.",
      "discord": "cornelius_",
      "flags": {}
    }
  ],
  "relationships": {
    "systems": [],
    "requires": []
  },
  "packs": [
    {
      "name": "deities-of-hucaen",
      "label": "Deities of Hucaen",
      "path": "packs/deities-of-hucaen",
      "type": "Item",
      "ownership": {
        "PLAYER": "OBSERVER",
        "ASSISTANT": "OWNER"
      },
      "system": "pf2e",
      "banner": "systems/pf2e/assets/compendium-banner/green.webp",
      "flags": {}
    },
    {
      "name": "maps-of-hucaen",
      "label": "Maps of Hucaen",
      "path": "packs/maps-of-hucaen",
      "type": "Scene",
      "ownership": {
        "PLAYER": "OBSERVER",
        "ASSISTANT": "OWNER"
      },
      "flags": {}
    },
    {
      "name": "npcs-of-hucaen",
      "label": "NPCs of Hucaen",
      "path": "packs/npcs-of-hucaen",
      "type": "Actor",
      "ownership": {
        "PLAYER": "OBSERVER",
        "ASSISTANT": "OWNER"
      },
      "system": "pf2e",
      "flags": {}
    },
    {
      "name": "tables-of-hucaen",
      "label": "Tables of hucaen",
      "path": "packs/tables-of-hucaen",
      "type": "RollTable",
      "ownership": {
        "PLAYER": "OBSERVER",
        "ASSISTANT": "OWNER"
      },
      "flags": {}
    },
    {
      "name": "journals-of-hucaen",
      "label": "Journals of Hucaen",
      "path": "packs/journals-of-hucaen",
      "type": "JournalEntry",
      "ownership": {
        "PLAYER": "OBSERVER",
        "ASSISTANT": "OWNER"
      },
      "flags": {}
    },
    {
      "name": "items-of-hucaen",
      "label": "Items of Hucaen",
      "path": "packs/items-of-hucaen",
      "system": "pf2e",
      "type": "Item",
      "ownership": {
        "PLAYER": "OBSERVER",
        "ASSISTANT": "OWNER"
      },
      "flags": {}
    }
  ],
  "packFolders": [
    {
      "name" : "The Realm of Hucaen",
      "packs": [
        "deities-of-hucaen",
        "tables-of-hucaen",
        "journals-of-hucaen",
        "npcs-of-hucaen",
        "maps-of-hucaen",
        "items-of-hucaen"
      ]
    }
  ],
  "url": "#{URL}#",
  "manifest": "#{MANIFEST}#",
  "download": "#{DOWNLOAD}#",
  "license": "LICENSE",
  "readme": "README.md",
  "media": [
    {
      "type": "icon",
      "url": "https://avatars2.githubusercontent.com/u/71292812?s=400&u=ccdb4eeb7abf551ca8f314e5a9bfd0479a4d3d41&v=4"
    }
  ]
}